pyphrasy/README.md
pyphrasy/__init__.py
pyphrasy/app.py
pyphrasy/inflect.py
pyphrasy/test.py
pyphrasy/static/css/bootstrap.min.css
pyphrasy/static/css/main.css
pyphrasy/static/js/main.js
pyphrasy/templates/index.html
pyphrasy-0.1.dist-info/METADATA
pyphrasy-0.1.dist-info/WHEEL
pyphrasy-0.1.dist-info/top_level.txt
pyphrasy-0.1.dist-info/RECORD
