Metadata-Version: 2.1
Name: pyphrasy
Version: 0.1
Summary: Inflection russian collocations based on pymorphy2
Home-page: https://github.com/summerisgone/pyphrasy
Author: UNKNOWN
Author-email: UNKNOWN
License: GNU Lesser General Public License (LGPL), Version 3
Keywords: pyhprasy pymorphy inflection phrases
Platform: UNKNOWN
Classifier: Environment :: Console
Classifier: Intended Audience :: Developers
Classifier: Intended Audience :: Information Technology
Classifier: License :: OSI Approved :: GNU Library or Lesser General Public License (LGPL)
Classifier: Programming Language :: Python
Classifier: Programming Language :: Python :: 2
Classifier: Programming Language :: Python :: 2.6
Classifier: Programming Language :: Python :: 2.7
Classifier: Programming Language :: Python :: 3
Classifier: Programming Language :: Python :: 3.2
Classifier: Programming Language :: Python :: 3.3
Classifier: Programming Language :: Python :: 3.4
Classifier: Topic :: Scientific/Engineering :: Information Analysis
Classifier: Topic :: Software Development :: Libraries :: Python Modules
Provides: pyphrasy
